templateco_cli/.DS_Store
templateco_cli/README.md
templateco_cli/__init__.py
templateco_cli/__main__.py
templateco_cli/poetry.lock
templateco_cli/pyproject.toml
templateco_cli-0.1.1.dist-info/entry_points.txt
templateco_cli-0.1.1.dist-info/WHEEL
templateco_cli-0.1.1.dist-info/METADATA
templateco_cli-0.1.1.dist-info/RECORD
