Metadata-Version: 2.1
Name: templateco-cli
Version: 0.1.1
Summary: 
License: MIT
Author: Mike Gregory
Author-email: mike.ja.gregory@gmail.com
Requires-Python: >=3.7,<4.0
Classifier: License :: OSI Approved :: MIT License
Classifier: Programming Language :: Python :: 3
Classifier: Programming Language :: Python :: 3.10
Classifier: Programming Language :: Python :: 3.7
Classifier: Programming Language :: Python :: 3.8
Classifier: Programming Language :: Python :: 3.9
Requires-Dist: templateco (>=0,<1)
Requires-Dist: typer (>=0.3,<0.5)
